{
    "count": 15,
    "clients": [
        {
            "clientID": 10633,
            "name": "DevOps",
            "email": "",
            "phone": "+7 (937) 028-89-32",
            "gender": 2,
            "birthday": "null.null.null",
            "status": 0,
            "blockingOnline": 0,
            "sale": "",
            "comment": "",
            "avatar": "",
            "crop": "",
            "revenue": 0,
            "percent": 0,
            "check": 0,
            "lastVisit": ""
        },
        {
            "clientID": 10632,
            "name": "Александр",
            "email": "",
            "phone": "+7 (927) 626-55-66",
            "gender": 2,
            "birthday": "",
            "status": 0,
            "blockingOnline": 0,
            "sale": "",
            "comment": "",
            "avatar": "",
            "crop": "",
            "revenue": 0,
            "percent": 0,
            "check": 0,
            "lastVisit": ""
        },
        {
            "clientID": 10920,
            "name": "Алексей",
            "email": "",
            "phone": "+7 (927) 055-29-23",
            "gender": 2,
            "birthday": "",
            "status": 0,
            "blockingOnline": 0,
            "sale": "",
            "comment": "",
            "avatar": "",
            "crop": "",
            "revenue": 0,
            "percent": 0,
            "check": 0,
            "lastVisit": ""
        },
        {
            "clientID": 10888,
            "name": "Анастасия Финогенова",
            "email": "",
            "phone": "+7 (917) 320-25-47",
            "gender": 2,
            "birthday": "null.null.null",
            "status": 0,
            "blockingOnline": 0,
            "sale": "",
            "comment": "",
            "avatar": "",
            "crop": "",
            "revenue": 0,
            "percent": 0,
            "check": 0,
            "lastVisit": ""
        },
        {
            "clientID": 10114,
            "name": "Анджелина Джоли",
            "email": "",
            "phone": "+7 (xxx) xxx-xx-xx",
            "gender": 0,
            "birthday": "",
            "status": 0,
            "blockingOnline": 0,
            "sale": "",
            "comment": "",
            "avatar": "040cb78dcbad6fc2e3697c4b65662b62.jpg",
            "crop": "{\"x\": 0, \"y\": 0, \"width\": 150, \"height\": 150}",
            "revenue": 0,
            "percent": 0,
            "check": 0,
            "lastVisit": ""
        },
        {
            "clientID": 14358,
            "name": "Артем Кудин",
            "email": "",
            "phone": "+7 (927) 156-46-97",
            "gender": 2,
            "birthday": "",
            "status": 0,
            "blockingOnline": 0,
            "sale": "",
            "comment": "",
            "avatar": "",
            "crop": "",
            "revenue": 0,
            "percent": 0,
            "check": 0,
            "lastVisit": ""
        },
        {
            "clientID": 14886,
            "name": "Дима Улитин",
            "email": "",
            "phone": "+7 (908) 545-85-01",
            "gender": 0,
            "birthday": "null.null.null",
            "status": 0,
            "blockingOnline": 0,
            "sale": "",
            "comment": "",
            "avatar": "",
            "crop": "",
            "revenue": 0,
            "percent": 0,
            "check": 0,
            "lastVisit": ""
        },
        {
            "clientID": 19905,
            "name": "Из Браузера",
            "email": "",
            "phone": "+7 (353) 535-35-35",
            "gender": 0,
            "birthday": "null.null.null",
            "status": 0,
            "blockingOnline": 0,
            "sale": "",
            "comment": "",
            "avatar": "",
            "crop": "",
            "revenue": 0,
            "percent": 0,
            "check": 0,
            "lastVisit": ""
        },
        {
            "clientID": 20294,
            "name": "Клиентик",
            "email": "",
            "phone": "+7 (538) 953-85-93",
            "gender": 0,
            "birthday": "null.null.null",
            "status": 0,
            "blockingOnline": 0,
            "sale": "",
            "comment": "",
            "avatar": "",
            "crop": "",
            "revenue": 0,
            "percent": 0,
            "check": 0,
            "lastVisit": ""
        },
        {
            "clientID": 19895,
            "name": "Клиентик",
            "email": "",
            "phone": "+7 (853) 785-37-85",
            "gender": 0,
            "birthday": "null.null.null",
            "status": 0,
            "blockingOnline": 0,
            "sale": "",
            "comment": "",
            "avatar": "",
            "crop": "",
            "revenue": 0,
            "percent": 0,
            "check": 0,
            "lastVisit": ""
        },
        {
            "clientID": 19898,
            "name": "Клиентик 2",
            "email": "",
            "phone": "+7 (492) 859-35-89",
            "gender": 0,
            "birthday": "null.null.null",
            "status": 0,
            "blockingOnline": 0,
            "sale": "",
            "comment": "",
            "avatar": "",
            "crop": "",
            "revenue": 0,
            "percent": 0,
            "check": 0,
            "lastVisit": ""
        },
        {
            "clientID": 19119,
            "name": "Максим",
            "email": "",
            "phone": "+7 (927) 627-10-75",
            "gender": 0,
            "birthday": "null.null.null",
            "status": 0,
            "blockingOnline": 0,
            "sale": "",
            "comment": "",
            "avatar": "",
            "crop": "",
            "revenue": 0,
            "percent": 0,
            "check": 0,
            "lastVisit": ""
        },
        {
            "clientID": 14674,
            "name": "Новый клиент",
            "email": "",
            "phone": "+7 (917) 320-25-40",
            "gender": 0,
            "birthday": "null.null.null",
            "status": 0,
            "blockingOnline": 0,
            "sale": "",
            "comment": "",
            "avatar": "",
            "crop": "",
            "revenue": 0,
            "percent": 0,
            "check": 0,
            "lastVisit": ""
        },
        {
            "clientID": 19872,
            "name": "оалс",
            "email": "",
            "phone": "+7 (679) 067-66-76",
            "gender": 0,
            "birthday": "null.null.null",
            "status": 0,
            "blockingOnline": 0,
            "sale": "",
            "comment": "",
            "avatar": "",
            "crop": "",
            "revenue": 0,
            "percent": 0,
            "check": 0,
            "lastVisit": ""
        },
        {
            "clientID": 11944,
            "name": "Студия красоты «Берёзка»",
            "email": "",
            "phone": "+7 (937) 140-04-44",
            "gender": 2,
            "birthday": "",
            "status": 0,
            "blockingOnline": 0,
            "sale": "",
            "comment": "",
            "avatar": "",
            "crop": "",
            "revenue": 0,
            "percent": 0,
            "check": 0,
            "lastVisit": ""
        }
    ],
    "general": {
        "revenue": 0,
        "percent": 100,
        "check": 0,
        "bidsCount": 0,
        "lastVisit": "",
        "typeName": ""
    }
}
